hdporncomics/__init__.py
hdporncomics/__main__.py
hdporncomics/args.py
hdporncomics/cli.py
hdporncomics/hdporncomics.py
hdporncomics-0.0.13.dist-info/licenses/LICENSE
hdporncomics-0.0.13.dist-info/METADATA
hdporncomics-0.0.13.dist-info/WHEEL
hdporncomics-0.0.13.dist-info/entry_points.txt
hdporncomics-0.0.13.dist-info/top_level.txt
hdporncomics-0.0.13.dist-info/RECORD
