Metadata-Version: 2.4
Name: hdporncomics
Version: 0.0.13
Summary: A full api for hdporncomics
Author-email: Dominik Stanisław Suchora <hexderm@gmail.com>
License: GPLv3
Project-URL: Homepage, https://github.com/TUVIMEN/hdporncomics
Keywords: text-processing,scraper,api,hdporncomics
Classifier: Development Status :: 5 - Production/Stable
Classifier: License :: OSI Approved :: GNU General Public License v3 (GPLv3)
Classifier: Operating System :: OS Independent
Classifier: Framework :: Pytest
Classifier: Programming Language :: Python :: 3
Classifier: Programming Language :: Python :: 3.8
Classifier: Programming Language :: Python :: 3.9
Classifier: Programming Language :: Python :: 3.10
Classifier: Programming Language :: Python :: 3.11
Classifier: Programming Language :: Python :: 3.12
Classifier: Programming Language :: Python :: 3.13
Classifier: Programming Language :: Python :: 3 :: Only
Requires-Python: >=3.8
License-File: LICENSE
Requires-Dist: requests
Requires-Dist: reliq
Requires-Dist: treerequests
Provides-Extra: test
Requires-Dist: pytest; extra == "test"
Requires-Dist: biggusdictus; extra == "test"
Provides-Extra: pdf
Requires-Dist: img2pdf; extra == "pdf"
Dynamic: license-file
